lakehouse/__init__.py
lakehouse/asset.py
lakehouse/cli.py
lakehouse/computation.py
lakehouse/decorators.py
lakehouse/errors.py
lakehouse/house.py
lakehouse/multi_type_storage.py
lakehouse/queryable_asset_set.py
lakehouse/storage.py
lakehouse/table.py
lakehouse/version.py
lakehouse-0.12.15.dist-info/LICENSE
lakehouse-0.12.15.dist-info/METADATA
lakehouse-0.12.15.dist-info/WHEEL
lakehouse-0.12.15.dist-info/entry_points.txt
lakehouse-0.12.15.dist-info/top_level.txt
lakehouse-0.12.15.dist-info/RECORD
