Metadata-Version: 2.1
Name: lakehouse
Version: 0.12.15
Summary: UNKNOWN
Home-page: https://github.com/dagster-io/dagster/tree/master/python_modules/libraries/lakehouse
Author: Elementl
Author-email: hello@elementl.com
License: Apache-2.0
Platform: UNKNOWN
Classifier: Programming Language :: Python :: 3.6
Classifier: Programming Language :: Python :: 3.7
Classifier: Programming Language :: Python :: 3.8
Classifier: License :: OSI Approved :: Apache Software License
Classifier: Operating System :: OS Independent
Requires-Dist: dagster (==0.12.15)
